rustpy_toolkit-0.1.2.dist-info/METADATA
rustpy_toolkit-0.1.2.dist-info/WHEEL
rustpy_toolkit-0.1.2.dist-info/licenses/LICENSE
rustpy_toolkit/__init__.py
rustpy_toolkit/__init__.pyi
rustpy_toolkit/__pycache__/__init__.cpython-312.pyc
rustpy_toolkit/__pycache__/polars_expressions.cpython-312.pyc
rustpy_toolkit/polars_expressions.py
rustpy_toolkit/py.typed
rustpy_toolkit/rustpy_toolkit.cpython-312-x86_64-linux-gnu.so
rustpy_toolkit/validation/__init__.py
rustpy_toolkit/validation/__init__.pyi
rustpy_toolkit/validation/__pycache__/__init__.cpython-312.pyc
rustpy_toolkit/validation/__pycache__/cpf_cnpj.cpython-312.pyc
rustpy_toolkit/validation/cpf_cnpj.py
rustpy_toolkit/validation/cpf_cnpj.pyi
rustpy_toolkit-0.1.2.dist-info/RECORD
