Metadata-Version: 2.4
Name: rustpy-toolkit
Version: 0.1.2
Classifier: Development Status :: 3 - Alpha
Classifier: Intended Audience :: Developers
Classifier: License :: OSI Approved :: MIT License
Classifier: Programming Language :: Python :: 3
Classifier: Programming Language :: Python :: 3.8
Classifier: Programming Language :: Python :: 3.9
Classifier: Programming Language :: Python :: 3.10
Classifier: Programming Language :: Python :: 3.11
Classifier: Programming Language :: Python :: 3.12
Classifier: Programming Language :: Rust
Requires-Dist: polars>=1.8.2
Requires-Dist: polars>=0.20.0 ; extra == 'polars'
Provides-Extra: polars
License-File: LICENSE
Summary: Rust toolkit for Python
Author-email: bellanda <gustavocasadeibellanda@gmail.com>
License: MIT
Requires-Python: >=3.8
